rfscope/__init__.py
rfscope-0.1.1.dist-info/licenses/LICENSE
rfscope-0.1.1.dist-info/METADATA
rfscope-0.1.1.dist-info/WHEEL
rfscope-0.1.1.dist-info/top_level.txt
rfscope-0.1.1.dist-info/RECORD
